exeteracovid/__init__.py
exeteracovid/algorithms/__init__.py
exeteracovid/algorithms/age_from_year_of_birth.py
exeteracovid/algorithms/assessment_merge.py
exeteracovid/algorithms/combined_healthcare_worker.py
exeteracovid/algorithms/consolidated_test_dates.py
exeteracovid/algorithms/convert_assessment_tests.py
exeteracovid/algorithms/convert_old_assessments.py
exeteracovid/algorithms/covid_test.py
exeteracovid/algorithms/effective_test_date.py
exeteracovid/algorithms/healthy_diet_index.py
exeteracovid/algorithms/inconsistent_symptoms.py
exeteracovid/algorithms/inconsistent_testing.py
exeteracovid/algorithms/method_paper_model.py
exeteracovid/algorithms/nat_medicine_model.py
exeteracovid/algorithms/temperature.py
exeteracovid/algorithms/test_type_from_mechanism.py
exeteracovid/algorithms/weight_height_bmi.py
exeteracovid/processing/__init__.py
exeteracovid/processing/parsing_schemas.py
exeteracovid/processing/postprocess.py
exeteracovid-0.2.0.1.dist-info/LICENSE
exeteracovid-0.2.0.1.dist-info/LICENSE.txt
exeteracovid-0.2.0.1.dist-info/METADATA
exeteracovid-0.2.0.1.dist-info/WHEEL
exeteracovid-0.2.0.1.dist-info/top_level.txt
exeteracovid-0.2.0.1.dist-info/RECORD
